pyxelperfect/__init__.py
pyxelperfect/decorators.py
pyxelperfect/diagnose.py
pyxelperfect/display.py
pyxelperfect/extract.py
pyxelperfect/manipulate.py
pyxelperfect/measure.py
pyxelperfect/project.py
pyxelperfect/qc.py
pyxelperfect/register.py
pyxelperfect/segment.py
pyxelperfect/stitch.py
pyxelperfect/threshold.py
pyxelperfect/tiling.py
pyxelperfect/transform_point.py
pyxelperfect/utils.py
pyxelperfect/workflows.py
pyxelperfect-0.1.10.dist-info/LICENSE
pyxelperfect-0.1.10.dist-info/METADATA
pyxelperfect-0.1.10.dist-info/WHEEL
pyxelperfect-0.1.10.dist-info/top_level.txt
pyxelperfect-0.1.10.dist-info/RECORD
