Metadata-Version: 2.1
Name: pyxelperfect
Version: 0.1.10
Summary: Collection of python powered image-processing functions
Home-page: https://github.com/sifrimlab/pyxelperfect
Author: LMIB
Author-email: david.wouters@kuleuven.be
Project-URL: Bug Reports, https://github.com/sifrimlab/pyxelperfect
Project-URL: Source, https://github.com/sifrimlab/pyxelperfect
Keywords: image-processing
Classifier: Development Status :: 3 - Alpha
Classifier: Topic :: Scientific/Engineering :: Bio-Informatics
Classifier: License :: OSI Approved :: GNU Affero General Public License v3
Classifier: Programming Language :: Python :: 3
Classifier: Programming Language :: Python :: 3.8
Requires-Python: >=3.8
License-File: LICENSE
Requires-Dist: numpy
Requires-Dist: tqdm
Requires-Dist: scikit-image
Requires-Dist: opencv-python-headless
Requires-Dist: pandas
Requires-Dist: aicspylibczi
Requires-Dist: matplotlib
Requires-Dist: Pillow
Requires-Dist: tifffile
Requires-Dist: tabulate
Requires-Dist: nd2reader
Requires-Dist: SimpleITK
Requires-Dist: joblib
Provides-Extra: tensor
Requires-Dist: tensorflow ; extra == 'tensor'
Requires-Dist: csbdeep ; extra == 'tensor'
Requires-Dist: stardist ; extra == 'tensor'
Requires-Dist: cellpose ; extra == 'tensor'
